INSTALL.rst
LICENSE
MANIFEST.in
README.rst
VERSION
requirements.txt
setup.py
tasks.py
src/pacbum/__init__.py
src/pacbum/__main__.py
src/pacbum/__meta__.py
src/pacbum/background.py
src/pacbum/colectScreen.py
src/pacbum/colectScreen_2.py
src/pacbum/environment.py
src/pacbum/environment2.py
src/pacbum/instructionsColectScreen.py
src/pacbum/mainPACBUM.py
src/pacbum/menuPacBum.py
src/pacbum/objects.py
src/pacbum/pacBum.py
src/pacbum/screenCredits.py
src/pacbum/textClass.py
src/pacbum.egg-info/PKG-INFO
src/pacbum.egg-info/SOURCES.txt
src/pacbum.egg-info/dependency_links.txt
src/pacbum.egg-info/entry_points.txt
src/pacbum.egg-info/not-zip-safe
src/pacbum.egg-info/requires.txt
src/pacbum.egg-info/top_level.txt
src/pacbum/assets/sfx/Blob-Monsters-on-the-Loose.wav
src/pacbum/assets/sfx/Cheesy-Science.wav
src/pacbum/assets/sfx/Clunky-Old-Time-Piano.wav
src/pacbum/assets/sfx/Explosion8.wav
src/pacbum/assets/sfx/PowerDown13.wav
src/pacbum/assets/sfx/PowerDown16.wav
src/pacbum/assets/sfx/PowerUp10.wav
src/pacbum/assets/sfx/PowerUp16.wav
src/pacbum/assets/sfx/Spooky-Island.mp3
src/pacbum/assets/sfx/Spooky-Island.wav
src/pacbum/assets/sfx/UI_Quirky27.wav
src/pacbum/assets/sfx/UI_Quirky28.wav
src/pacbum/images/alien_c2_pb.png
src/pacbum/images/amphibian_dino_c2_pb.png
src/pacbum/images/bg_colect_screen.png
src/pacbum/images/bg_colect_screen_2.png
src/pacbum/images/bg_colect_screen_3.png
src/pacbum/images/bg_credits_pb.png
src/pacbum/images/bg_instructions_pb.png
src/pacbum/images/bg_menu.png
src/pacbum/images/bg_menu_back.png
src/pacbum/images/bg_menu_pb.png
src/pacbum/images/bg_textscreen_pb.png
src/pacbum/images/bum_stone_c2_pb.png
src/pacbum/images/coconut_bomb_c2_pb.png
src/pacbum/images/coconut_venom_c2_pb.png
src/pacbum/images/cow_skull.png
src/pacbum/images/credits_bt.png
src/pacbum/images/exit_bt.png
src/pacbum/images/final_scene_pb.png
src/pacbum/images/fire_stone_c2_pb.png
src/pacbum/images/flag.png
src/pacbum/images/flag_dead.png
src/pacbum/images/flag_next_level.png
src/pacbum/images/flag_pause.png
src/pacbum/images/fly_pb_bw.png
src/pacbum/images/fly_pb_fw.png
src/pacbum/images/life_c2_pb.png
src/pacbum/images/options_bt.png
src/pacbum/images/pac_bomb.png
src/pacbum/images/pac_branch.png
