Metadata-Version: 1.1
Name: pacbum
Version: 1.0.1
Summary: The Lord of the Time! PacBUm!
Home-page: https://github.com/fis-jogos/ep1-ls
Author: Lucas S. Souza
Author-email: lucas.soaresouza@gmail.com
License: UNKNOWN
Platform: any
Classifier: Development Status :: 3 - Alpha
Classifier: Intended Audience :: Developers
Classifier: License :: OSI Approved :: GNU General Public License (GPL)
Classifier: Operating System :: OS Independent
Classifier: Programming Language :: Python
Classifier: Programming Language :: Python :: 3
Classifier: Programming Language :: Python :: 3.3
Classifier: Programming Language :: Python :: 3.4
Classifier: Programming Language :: Python :: 3.5
Classifier: Topic :: Software Development :: Libraries
